hierogliff/__init__.py
hierogliff/src/__init__.py
hierogliff/src/function.py
hierogliff/src/node/__init__.py
hierogliff/src/node/functions.py
hierogliff/src/node/node.py
hierogliff/src/node/dual/__init__.py
hierogliff/src/node/dual/dual.py
hierogliff/src/node/dual/functions.py
hierogliff/tests/__init__.py
hierogliff/tests/node/__init__.py
Hierogliff-0.4.dist-info/LICENSE
Hierogliff-0.4.dist-info/METADATA
Hierogliff-0.4.dist-info/WHEEL
Hierogliff-0.4.dist-info/top_level.txt
Hierogliff-0.4.dist-info/RECORD
