Metadata-Version: 2.1
Name: Hierogliff
Version: 0.4
Summary: The package hierogliff performs automatic differentiation
Home-page: https://github.com/cs107-hierogliff/cs107-FinalProject/blob/main/docs/DOCUMENTATION.md
Author: Stella Ituze | Kishan Venkataramu | Maxime Laasri | Lara Zeng
Author-email: ituzes@college.harvard.edu
License: UNKNOWN
Platform: UNKNOWN
Classifier: Programming Language :: Python :: 3
Classifier: License :: OSI Approved :: MIT License
Classifier: Operating System :: OS Independent
Requires-Python: >=3.6
License-File: LICENSE
Requires-Dist: numpy
Requires-Dist: pytest
